setup.py
pyqt_mess_server.egg-info/PKG-INFO
pyqt_mess_server.egg-info/SOURCES.txt
pyqt_mess_server.egg-info/dependency_links.txt
pyqt_mess_server.egg-info/requires.txt
pyqt_mess_server.egg-info/top_level.txt
server/__init__.py
server/server.py
server/server_run.py
server/common/__init__.py
server/common/decos.py
server/common/descryptors.py
server/common/errors.py
server/common/metaclasses.py
server/common/utils.py
server/common/variables.py
server/server/__init__.py
server/server/add_user.py
server/server/config_window.py
server/server/core.py
server/server/database.py
server/server/main_window.py
server/server/remove_user.py
server/server/stat_window.py
server/unit_tests/__init__.py
server/unit_tests/test_utils.py