Metadata-Version: 1.0
Name: pyqt-mess-server
Version: 0.1.2
Summary: MessLex Server
Home-page: UNKNOWN
Author: Ivan Ivanov
Author-email: iv.iv@yandex.ru
License: UNKNOWN
Platform: UNKNOWN
